[
      {
        "regno" : "2f27a562-91c9-4b2b-85a8-268cc9d53c93",
        "roomname" : "754-Mumbai",
        "description": "Meeting Room",
        "capacity": 20,
        "skypeenabled":false,
        "projectorenabled":true,
        "tvenabled":false,
        "telenabled":true,
        "status": true
      },
      {
        "regno" : "62512e2a-fc34-4799-8641-b0b21fbe15c1",
        "roomname" : "753-Delhi",
        "description": "Meeting Room",
        "capacity": 8,
        "skypeenabled":true,
        "projectorenabled":false,
        "tvenabled":true,
        "telenabled":true,
        "status": false
      },
      {
        "regno" : "0eb72656-1a67-4b9e-a2a9-cdec0bc3d51a",
        "roomname" : "752-Bengaluru",
        "description": "Board Room",
        "capacity": 40,
        "skypeenabled":true,
        "projectorenabled":true,
        "tvenabled":true,
        "telenabled":true,
        "status": true
      },
      {
        "regno" : "860dd9b2-0dee-49f4-8ddf-516e02034eb1",
        "roomname" : "710-Chennai",
        "description": "Meeting Room",
        "capacity": 10,
        "skypeenabled":true,
        "projectorenabled":false,
        "tvenabled":true,
        "telenabled":true,
        "status": false
      },
      {
        "regno" : "0648cd1a-396b-40cc-a559-724c8479e0bc",
        "roomname" : "712-Kerala",
        "description": "Recreation Room",
        "capacity": 100,
        "skypeenabled":false,
        "projectorenabled":false,
        "tvenabled":true,
        "telenabled":false,
        "status": true
      },
      {
        "regno" : "47c6107b-a751-4d3a-b7ae-9c510450c033",
        "roomname" : "720-Hyderabad",
        "description": "Meeting Room",
        "capacity": 20,
        "skypeenabled":false,
        "projectorenabled":true,
        "tvenabled":false,
        "telenabled":true,
        "status": false
      }
    ]
